bcp/bcp_utils/__init__.py
bcp/bcp_utils/bulk_insert.py
py_bcp_utils-0.1.1.dist-info/METADATA
py_bcp_utils-0.1.1.dist-info/WHEEL
py_bcp_utils-0.1.1.dist-info/top_level.txt
py_bcp_utils-0.1.1.dist-info/RECORD
