Metadata-Version: 2.4
Name: py-bcp-utils
Version: 0.1.1
Summary: A utility to run BCP bulk inserts from a Pandas DataFrame.
Author-email: João Afonso <contact.joaoafonso@gmail.com>
License-Expression: MIT
Project-URL: Homepage, https://github.com/Afonso-13/py-bcp-utils
Classifier: Programming Language :: Python :: 3
Classifier: Operating System :: OS Independent
Classifier: Topic :: Database
Requires-Python: >=3.8
Requires-Dist: pandas>=1.0.0
